axpy/__about__.py
axpy/__init__.py
axpy/mip.py
axpy/plastic.py
axpy/plot.py
axpy-0.0.5.dist-info/METADATA
axpy-0.0.5.dist-info/WHEEL
axpy-0.0.5.dist-info/licenses/LICENSE.txt
axpy-0.0.5.dist-info/RECORD
