Metadata-Version: 2.1
Name: axpy
Version: 0.0.5
Summary: A Python package for Auxetics
Project-URL: Documentation, https://github.com/unknown/axpy#readme
Project-URL: Issues, https://github.com/unknown/axpy/issues
Project-URL: Source, https://github.com/unknown/axpy
Author-email: gv-sh <gv-sh@outlook.com>
License-File: LICENSE.txt
Classifier: Development Status :: 4 - Beta
Classifier: Programming Language :: Python
Classifier: Programming Language :: Python :: 3.7
Classifier: Programming Language :: Python :: 3.8
Classifier: Programming Language :: Python :: 3.9
Classifier: Programming Language :: Python :: 3.10
Classifier: Programming Language :: Python :: 3.11
Classifier: Programming Language :: Python :: Implementation :: CPython
Classifier: Programming Language :: Python :: Implementation :: PyPy
Requires-Python: >=3.7
Requires-Dist: matplotlib
Requires-Dist: numpy
Requires-Dist: opencv-python
Requires-Dist: pandas
